montagne/__init__.py
montagne-0.0.0.dist-info/LICENSE
montagne-0.0.0.dist-info/METADATA
montagne-0.0.0.dist-info/WHEEL
montagne-0.0.0.dist-info/top_level.txt
montagne-0.0.0.dist-info/RECORD
