Metadata-Version: 2.2
Name: montagne
Version: 0.0.0
Summary: Montagne frontend framework that speaks fluent Python.
Author-email: Ali Chaayb <achaaybdev@gmail.com>
License: MIT
Project-URL: repository, https://github.com/achaayb/montagne
License-File: LICENSE
